truck_telemetry/__init__.py
truck_telemetry/truck_telemetry.py
truck_telemetry/version.py
truck_telemetry/telemetry_version/__init__.py
truck_telemetry/telemetry_version/unpack.py
truck_telemetry/telemetry_version/v1_10.py
truck_telemetry/telemetry_version/v1_12.py
truck_telemetry-0.0.3.dist-info/LICENSE
truck_telemetry-0.0.3.dist-info/METADATA
truck_telemetry-0.0.3.dist-info/WHEEL
truck_telemetry-0.0.3.dist-info/top_level.txt
truck_telemetry-0.0.3.dist-info/RECORD
