Metadata-Version: 2.1
Name: truck_telemetry
Version: 0.0.3
Summary: SCS Telemetry for EuroTruckSimulator 2 and AmericanTruckSimulator
Home-page: https://github.com/dreagonmon/truck_telemetry
Author: Dreagonmon
Author-email: 531486058@qq.com
Keywords: development
Classifier: Programming Language :: Python :: 3
Classifier: License :: OSI Approved :: MIT License
Requires-Python: >=3.6
License-File: LICENSE
